{"version":{"fullVersion":"1.3.3","major":"1","minor":"3","patch":"3"},"meta":{"flags":["experimentalData","isomorphicGitBridge"]},"collections":[{"label":"English","name":"english","path":"content/english","fields":[{"type":"rich-text","name":"body","label":"Body of Document","description":"This is the markdown body","isBody":true,"namespace":["english","body"]},{"type":"string","name":"title","label":"title","namespace":["english","title"]},{"type":"string","name":"slug","label":"slug","required":true,"namespace":["english","slug"]},{"type":"string","name":"description","label":"description","namespace":["english","description"]},{"type":"string","name":"summary","label":"summary","ui":{"component":"textarea"},"namespace":["english","summary"]},{"type":"datetime","name":"date","label":"date","namespace":["english","date"]},{"type":"string","name":"translationKey","label":"translationKey","namespace":["english","translationKey"]},{"type":"boolean","name":"toc","label":"table of contents","namespace":["english","toc"]}],"namespace":["english"]},{"label":"French","name":"french","path":"content/french","fields":[{"type":"rich-text","name":"body","label":"Body of Document","description":"This is the markdown body","isBody":true,"namespace":["french","body"]}],"namespace":["french"]},{"label":"Pages","name":"pages","path":"content","fields":[{"type":"rich-text","name":"body","label":"Body of Document","description":"This is the markdown body","isBody":true,"namespace":["pages","body"]}],"namespace":["pages"]}],"config":{"media":{"tina":{"publicFolder":"static","mediaRoot":""}}}}